LICENSE
MANIFEST.in
README.rst
setup.py
threatstack/__init__.py
threatstack/base.py
threatstack/client.py
threatstack/errors.py
threatstack.egg-info/PKG-INFO
threatstack.egg-info/SOURCES.txt
threatstack.egg-info/dependency_links.txt
threatstack.egg-info/requires.txt
threatstack.egg-info/top_level.txt
threatstack/v1/__init__.py
threatstack/v1/client.py
threatstack/v1/resources.py
threatstack/v2/__init__.py
threatstack/v2/client.py
threatstack/v2/resources.py