Metadata-Version: 1.1
Name: threatstack
Version: 1.2.0
Summary: A Python client for the Threat Stack API
Home-page: https://github.com/MyPureCloud/threatstack-python-client
Author: Genesys Labs
Author-email: george.vauter@genesys.com
License: MIT License
Platform: UNKNOWN
Classifier: Development Status :: 4 - Beta
Classifier: Intended Audience :: Developers
Classifier: Intended Audience :: Information Technology
Classifier: Intended Audience :: System Administrators
Classifier: License :: OSI Approved :: MIT License
Classifier: Natural Language :: English
Classifier: Operating System :: POSIX :: Linux
Classifier: Programming Language :: Python
Classifier: Topic :: Security
